{
  "constants": {
      "camara_label": "camara",
      "senado_label": "senado"
  },
  
  "eventos_fases":[
    {"evento_num" : "primeiro_evento", "fase_global":"Pré-Construção"},
    {"evento_num" : "apresentacao_pl1", "fase_global":"Construção"},
    {"evento_num" : "virada_de_casa1", "fase_global":"Pré-Revisão I"},
    {"evento_num" : "apresentacao_pl2", "fase_global":"Revisão I"},
    {"evento_num" : "virada_de_casa2", "fase_global":"Pré-Revisão II"},
    {"evento_num" : "apresentacao_pl3", "fase_global":"Revisão II"},
    {"evento_num" : "remetida_a_sancao1", "fase_global":"Sanção/Veto"},
    {"evento_num" : "apresentacao_pl4", "fase_global":"Avaliação dos Vetos"}
  ],
  
  "fases_global_mpv":[
    {"fase_global":"Comissão Mista"},
    {"fase_global":"Câmara dos Deputados"},
    {"fase_global":"Senado Federal"},
    {"fase_global":"Câmara dos Deputados - Revisão"},
    {"fase_global":"Transformada em Lei"},
    {"fase_global":"Transformada em Lei com vetos"}
  ],

  "fases_global":[
    {"local": "", "fase_global": "Pré-Construção"},
    {"local": "Comissões", "fase_global": "Construção"},
    {"local": "Plenário", "fase_global": "Construção"},
    {"local": "", "fase_global": "Pré-Revisão I"},
    {"local": "Comissões", "fase_global": "Revisão I"},
    {"local": "Plenário", "fase_global": "Revisão I"},
    {"local": "", "fase_global": "Pré-Revisão II"},
    {"local": "Comissões", "fase_global": "Revisão II"},
    {"local": "Plenário", "fase_global": "Revisão II"},
    {"local": "Presidência da República", "fase_global": "Sanção/Veto"},
    {"local": "Congresso", "fase_global": "Avaliação dos Vetos"}
  ],

   "fase_global_sancao":{
    "situacao_sancao": "remetida_a_sancao",
    "situacao_norma_juridica": "transformada_em_norma_jurídica"
  },

  "tipos_eventos":[
    {"tipo":"despacho", "label":"Despacho", "peso":0.25},
    {"tipo":"discussao", "label":"Discussão", "peso":0.07},
    {"tipo":"votacao", "label":"Votação", "peso":0.68}
  ],

  "tipos_locais":[
    {"tipo":"decisivo", "label":"Decisivo", "peso":0.68}
  ],

  "eventos": [
    {"evento": null, "nivel": 3},
    {"evento": "requerimento_audiencia_publica", "titulo_evento": "Requerimento de Audiência Pública" ,"nivel": 1},
    {"evento": "aprovacao_parecer", "titulo_evento": "Aprovação de Parecer" , "nivel": 1},
    {"evento": "requerimento_seminario", "titulo_evento": "Requerimento de Seminário" , "nivel": 1},
    {"evento": "aprovacao_audiencia_publica", "titulo_evento": "Aprovação de Audiência Pública" , "nivel": 1},
    {"evento": "requerimento_redistribuicao", "titulo_evento": "Requerimento de Redistribuição" , "nivel": 1},
    {"evento": "requerimento_apensacao", "titulo_evento": "Requerimento de Apensação" , "nivel": 1},
    {"evento": "requerimento_urgencia", "titulo_evento": "Requerimento de Urgência" , "nivel": 1},
    {"evento": "requerimento_prorrogacao", "titulo_evento": "Requerimento de Prorrogação" , "nivel": 1},
    {"evento": "projeto_reconstituido", "titulo_evento": "Projeto Reconstituído" , "nivel": 2},
    {"evento": "desarquivamento", "titulo_evento": "Desarquivamento" , "nivel": 1},
    {"evento": "alteracao_de_regime", "titulo_evento": "Alteração de Regime de Tramitação" , "nivel": 1},
    {"evento": "redistribuicao", "titulo_evento": "Redistribuição" , "nivel": 1},
    {"evento": "distribuicao", "titulo_evento": "Distribuição" , "nivel": 2},
    {"evento": "comissao_especial", "titulo_evento": "Comissão Especial" , "nivel": 2},
    {"evento": "designado_relator", "titulo_evento": "Designação de Relator" , "nivel": 1},
    {"evento": "voto_em_separado", "titulo_evento": "Voto em Separado" , "nivel": 2},
    {"evento": "apresentacao_pl", "titulo_evento": "Apresentação de Projeto de Lei" , "nivel": 2},
    {"evento": "retirada_de_pauta", "titulo_evento": "Retirada de Pauta" , "nivel": 2},
    {"evento": "pedido_de_vista", "titulo_evento": "Pedido de Vista" , "nivel": 2},
    {"evento": "inicio_prazo_emendas", "titulo_evento": "Início do Prazo para Emendas" , "nivel": 1},
    {"evento": "fim_prazo_emendas", "titulo_evento": "Fim do Prazo para Emendas" , "nivel": 1},
    {"evento": "arquivamento", "titulo_evento": "Arquivamento" , "nivel": 2},
    {"evento": "parecer_pela_adequacao_financeira_e_orcamentaria", "titulo_evento": "Parecer pela Adequação Financeira e Orçamentária" , "nivel": 1},
    {"evento": "parecer_pela_aprovacao_com_substitutivo", "titulo_evento": "Parecer pela Aprovação com Substitutivo" , "nivel": 1},
    {"evento": "parecer_pela_aprovacao", "titulo_evento": "Parecer pela Aprovação" , "nivel": 1},
    {"evento": "parecer_pela_rejeicao", "titulo_evento": "Parecer pela Rejeição" , "nivel": 1},
    {"evento": "parecer", "titulo_evento": "Parecer" , "nivel": 1},
    {"evento": "virada_de_casa", "titulo_evento": "Virada de Casa" , "nivel": 2},
    {"evento": "remetida_a_sancao", "titulo_evento": "Remetida à Sanção" , "nivel": 2},
    {"evento": "transformada_lei", "titulo_evento": "Transformada em Lei" , "nivel": 2},
    {"evento": "vetada_totalmente", "titulo_evento": "Vetada Totalmente" , "nivel": 1},
    {"evento": "parecer_comissao", "titulo_evento": "Parecer emitido na Comissão" , "nivel": 1},
    {"evento": "req_apresentacao", "titulo_evento": "Apresentação de" , "nivel": 1},
    {"evento": "req_deferido", "titulo_evento": "Deferimento de" , "nivel": 1},
    {"evento": "req_indeferido", "titulo_evento": "Indeferimento de" , "nivel": 1},
    {"evento": "req_arquivado", "titulo_evento": "Arquivamento de" , "nivel": 3},
    {"evento": "aprovacao_substitutivo", "titulo_evento": "Aprovação do Substitutivo" , "nivel": 1},
    {"evento": "realizacao_audiencia_publica", "titulo_evento": "Realização de Audiência Pública" , "nivel": 1},
    {"evento": "apresentacao_parecer", "titulo_evento": "Apresentação de Parecer" , "nivel": 1},
    {"evento": "devolvido", "titulo_evento": "Devolução do Projeto pelo Relator" , "nivel": 1},
    {"evento": "recebimento_comissao", "titulo_evento": "Recebimento na Comissão" , "nivel": 2},
    {"evento": "aprovacao_projeto", "titulo_evento": "Aprovação do Projeto" , "nivel": 1}
  ]
}
